venstarcolortouch/__init__.py
venstarcolortouch/__main__.py
venstarcolortouch/venstarcolortouch.py
venstarcolortouch-0.21.dist-info/LICENSE
venstarcolortouch-0.21.dist-info/METADATA
venstarcolortouch-0.21.dist-info/WHEEL
venstarcolortouch-0.21.dist-info/top_level.txt
venstarcolortouch-0.21.dist-info/RECORD
