Metadata-Version: 2.1
Name: venstarcolortouch
Version: 0.21
Summary: Interface Library for Venstar ColorTouch Thermostat API v5
Home-page: https://github.com/hpeyerl/venstar_colortouch
Author: Herb Peyerl
Author-email: hpeyerl+venstar@beer.org
Maintainer: Herb Peyerl
Maintainer-email: hpeyerl+venstar@beer.org
License: MIT
Keywords: thermostat
Platform: UNKNOWN
Classifier: Intended Audience :: Developers
Classifier: Programming Language :: Python
Classifier: Programming Language :: Python :: 2
Classifier: Programming Language :: Python :: 2.7
Classifier: Programming Language :: Python :: 3
Classifier: Programming Language :: Python :: 3.3
Classifier: Programming Language :: Python :: 3.4
Classifier: Programming Language :: Python :: 3.5
Classifier: License :: OSI Approved :: MIT License
License-File: LICENSE
Requires-Dist: requests (>=2.14.1)
